trav/__init__.py
trav/main.py
trav-0.0.2.dist-info/DESCRIPTION.rst
trav-0.0.2.dist-info/METADATA
trav-0.0.2.dist-info/RECORD
trav-0.0.2.dist-info/WHEEL
trav-0.0.2.dist-info/metadata.json
trav-0.0.2.dist-info/top_level.txt
