Metadata-Version: 2.0
Name: trav
Version: 0.0.2
Summary: A package to access Travis CI environment variables
Home-page: https://github.com/andrewda/trav
Author: Andrew Dassonville
Author-email: dassonville.andrew@gmail.com
License: MIT
Keywords: travis,ci,env
Platform: UNKNOWN
